<?xml version="1.0" encoding="UTF-8"?><PCD>
<Panoramas startdir="0" startpano="pano0" startfloor="B1"startcont="01" startname="シアター">
<Panorama panoid="pano0">
<img height="0" src="pano543.jpg" width="0"/>
<coords lat="34.668194883448315" lng="133.9162963628769"/>
<direction north="1180"/>
<chpanos>
<chpano panoid="pano1"><range end="54.0" start="306.0"/><fov base="85.0" next="105.0"/><correct pan="0.0" tilt="0.0"/></chpano>
<chpano panoid="pano8"><range end="305.0" start="218.0"/><fov base="85.0" next="105.0"/><correct pan="0.0" tilt="0.0"/></chpano>
</chpanos>
</Panorama>
<Panorama panoid="pano1">
<img height="0" src="pano544.jpg" width="0"/>
<coords lat="34.66821363452627" lng="133.9162963628769"/>
<direction north="1180"/>
<chpanos>
<chpano panoid="pano2"><range end="50.0" start="302.0"/><fov base="85.0" next="105.0"/><correct pan="0.0" tilt="0.0"/></chpano>
<chpano panoid="pano0"><range end="234.0" start="126.0"/><fov base="85.0" next="105.0"/><correct pan="0.0" tilt="0.0"/></chpano>
<chpano panoid="pano9"><range end="301.0" start="235.0"/><fov base="85.0" next="105.0"/><correct pan="0.0" tilt="0.0"/></chpano>
</chpanos>
</Panorama>
<Panorama panoid="pano2">
<img height="0" src="pano545.jpg" width="0"/>
<coords lat="34.66823238559998" lng="133.91629502177238"/>
<direction north="1180"/>
<chpanos>
<chpano panoid="pano3"><range end="54.0" start="306.0"/><fov base="85.0" next="105.0"/><correct pan="0.0" tilt="0.0"/></chpano>
<chpano panoid="pano1"><range end="230.0" start="122.0"/><fov base="85.0" next="105.0"/><correct pan="0.0" tilt="0.0"/></chpano>
<chpano panoid="pano10"><range end="305.0" start="231.0"/><fov base="85.0" next="105.0"/><correct pan="0.0" tilt="0.0"/></chpano>
</chpanos>
</Panorama>
<Panorama panoid="pano3">
<img height="0" src="pano546.jpg" width="0"/>
<coords lat="34.66825419354579" lng="133.9162954049451"/>
<direction north="1180"/>
<chpanos>
<chpano panoid="pano4"><range end="54.0" start="304.0"/><fov base="85.0" next="105.0"/><correct pan="0.0" tilt="0.0"/></chpano>
<chpano panoid="pano2"><range end="234.0" start="126.0"/><fov base="85.0" next="105.0"/><correct pan="0.0" tilt="0.0"/></chpano>
<chpano panoid="pano11"><range end="303.0" start="235.0"/><fov base="85.0" next="105.0"/><correct pan="0.0" tilt="0.0"/></chpano>
</chpanos>
</Panorama>
<Panorama panoid="pano4">
<img height="0" src="pano547.jpg" width="0"/>
<coords lat="34.66827245613631" lng="133.91629530915193"/>
<direction north="1180"/>
<chpanos>
<chpano panoid="pano5"><range end="54.0" start="304.0"/><fov base="85.0" next="105.0"/><correct pan="0.0" tilt="0.0"/></chpano>
<chpano panoid="pano3"><range end="234.0" start="124.0"/><fov base="85.0" next="105.0"/><correct pan="0.0" tilt="0.0"/></chpano>
<chpano panoid="pano12"><range end="303.0" start="235.0"/><fov base="85.0" next="105.0"/><correct pan="0.0" tilt="0.0"/></chpano>
</chpanos>
</Panorama>
<Panorama panoid="pano5">
<img height="0" src="pano548.jpg" width="0"/>
<coords lat="34.66829071872683" lng="133.91629521335875"/>
<direction north="1180"/>
<chpanos>
<chpano panoid="pano6"><range end="54.0" start="304.0"/><fov base="85.0" next="105.0"/><correct pan="0.0" tilt="0.0"/></chpano>
<chpano panoid="pano4"><range end="234.0" start="124.0"/><fov base="85.0" next="105.0"/><correct pan="0.0" tilt="0.0"/></chpano>
<chpano panoid="pano13"><range end="303.0" start="235.0"/><fov base="85.0" next="105.0"/><correct pan="0.0" tilt="0.0"/></chpano>
</chpanos>
</Panorama>
<Panorama panoid="pano6">
<img height="0" src="pano549.jpg" width="0"/>
<coords lat="34.668308981317345" lng="133.91629511756557"/>
<direction north="1180"/>
<chpanos>
<chpano panoid="pano7"><range end="54.0" start="304.0"/><fov base="85.0" next="105.0"/><correct pan="0.0" tilt="0.0"/></chpano>
<chpano panoid="pano5"><range end="234.0" start="124.0"/><fov base="85.0" next="105.0"/><correct pan="0.0" tilt="0.0"/></chpano>
<chpano panoid="pano13"><range end="303.0" start="235.0"/><fov base="85.0" next="105.0"/><correct pan="0.0" tilt="0.0"/></chpano>
</chpanos>
</Panorama>
<Panorama panoid="pano7">
<img height="0" src="pano550.jpg" width="0"/>
<coords lat="34.66832724390787" lng="133.91629502177238"/>
<direction north="1180"/>
<chpanos>
<chpano panoid="pano6"><range end="234.0" start="124.0"/><fov base="85.0" next="105.0"/><correct pan="0.0" tilt="0.0"/></chpano>
<chpano panoid="pano15"><range end="292.0" start="235.0"/><fov base="85.0" next="105.0"/><correct pan="0.0" tilt="0.0"/></chpano>
</chpanos>
</Panorama>
<Panorama panoid="pano8">
<img height="0" src="pano551.jpg" width="0"/>
<coords lat="34.668194883448315" lng="133.9162601530552"/>
<direction north="1180"/>
<chpanos>
<chpano panoid="pano9"><range end="50.0" start="302.0"/><fov base="85.0" next="105.0"/><correct pan="0.0" tilt="0.0"/></chpano>
<chpano panoid="pano0"><range end="142.0" start="51.0"/><fov base="85.0" next="105.0"/><correct pan="0.0" tilt="0.0"/></chpano>
<chpano panoid="pano16"><range end="301.0" start="215.0"/><fov base="85.0" next="105.0"/><correct pan="0.0" tilt="0.0"/></chpano>
</chpanos>
</Panorama>
<Panorama panoid="pano9">
<img height="0" src="pano552.jpg" width="0"/>
<coords lat="34.668214737530725" lng="133.91625881195068"/>
<direction north="1180"/>
<chpanos>
<chpano panoid="pano10"><range end="60.0" start="312.0"/><fov base="85.0" next="105.0"/><correct pan="0.0" tilt="0.0"/></chpano>
<chpano panoid="pano1"><range end="121.0" start="61.0"/><fov base="85.0" next="105.0"/><correct pan="0.0" tilt="0.0"/></chpano>
<chpano panoid="pano8"><range end="230.0" start="122.0"/><fov base="85.0" next="105.0"/><correct pan="0.0" tilt="0.0"/></chpano>
<chpano panoid="pano17"><range end="311.0" start="231.0"/><fov base="85.0" next="105.0"/><correct pan="0.0" tilt="0.0"/></chpano>
</chpanos>
</Panorama>
<Panorama panoid="pano10">
<img height="0" src="pano553.jpg" width="0"/>
<coords lat="34.668235694612555" lng="133.9162614941597"/>
<direction north="1180"/>
<chpanos>
<chpano panoid="pano11"><range end="50.0" start="302.0"/><fov base="85.0" next="105.0"/><correct pan="0.0" tilt="0.0"/></chpano>
<chpano panoid="pano2"><range end="131.0" start="51.0"/><fov base="85.0" next="105.0"/><correct pan="0.0" tilt="0.0"/></chpano>
<chpano panoid="pano9"><range end="240.0" start="132.0"/><fov base="85.0" next="105.0"/><correct pan="0.0" tilt="0.0"/></chpano>
<chpano panoid="pano18"><range end="301.0" start="241.0"/><fov base="85.0" next="105.0"/><correct pan="0.0" tilt="0.0"/></chpano>
</chpanos>
</Panorama>
<Panorama panoid="pano11">
<img height="0" src="pano554.jpg" width="0"/>
<coords lat="34.66825444568128" lng="133.9162601530552"/>
<direction north="1180"/>
<chpanos>
<chpano panoid="pano12"><range end="54.0" start="306.0"/><fov base="85.0" next="105.0"/><correct pan="0.0" tilt="0.0"/></chpano>
<chpano panoid="pano3"><range end="121.0" start="55.0"/><fov base="85.0" next="105.0"/><correct pan="0.0" tilt="0.0"/></chpano>
<chpano panoid="pano10"><range end="230.0" start="122.0"/><fov base="85.0" next="105.0"/><correct pan="0.0" tilt="0.0"/></chpano>
<chpano panoid="pano19"><range end="305.0" start="231.0"/><fov base="85.0" next="105.0"/><correct pan="0.0" tilt="0.0"/></chpano>
</chpanos>
</Panorama>
<Panorama panoid="pano12">
<img height="0" src="pano555.jpg" width="0"/>
<coords lat="34.66827319674577" lng="133.9162601530552"/>
<direction north="1180"/>
<chpanos>
<chpano panoid="pano13"><range end="54.0" start="306.0"/><fov base="85.0" next="105.0"/><correct pan="0.0" tilt="0.0"/></chpano>
<chpano panoid="pano4"><range end="125.0" start="55.0"/><fov base="85.0" next="105.0"/><correct pan="0.0" tilt="0.0"/></chpano>
<chpano panoid="pano11"><range end="234.0" start="126.0"/><fov base="85.0" next="105.0"/><correct pan="0.0" tilt="0.0"/></chpano>
<chpano panoid="pano20"><range end="305.0" start="235.0"/><fov base="85.0" next="105.0"/><correct pan="0.0" tilt="0.0"/></chpano>
</chpanos>
</Panorama>
<Panorama panoid="pano13">
<img height="0" src="pano556.jpg" width="0"/>
<coords lat="34.668291947806" lng="133.9162601530552"/>
<direction north="1180"/>
<chpanos>
<chpano panoid="pano14"><range end="54.0" start="306.0"/><fov base="85.0" next="105.0"/><correct pan="0.0" tilt="0.0"/></chpano>
<chpano panoid="pano5"><range end="125.0" start="55.0"/><fov base="85.0" next="105.0"/><correct pan="0.0" tilt="0.0"/></chpano>
<chpano panoid="pano12"><range end="234.0" start="126.0"/><fov base="85.0" next="105.0"/><correct pan="0.0" tilt="0.0"/></chpano>
<chpano panoid="pano21"><range end="305.0" start="235.0"/><fov base="85.0" next="105.0"/><correct pan="0.0" tilt="0.0"/></chpano>
</chpanos>
</Panorama>
<Panorama panoid="pano14">
<img height="0" src="pano557.jpg" width="0"/>
<coords lat="34.66831180186516" lng="133.9162601530552"/>
<direction north="1180"/>
<chpanos>
<chpano panoid="pano15"><range end="54.0" start="306.0"/><fov base="85.0" next="105.0"/><correct pan="0.0" tilt="0.0"/></chpano>
<chpano panoid="pano6"><range end="125.0" start="55.0"/><fov base="85.0" next="105.0"/><correct pan="0.0" tilt="0.0"/></chpano>
<chpano panoid="pano13"><range end="234.0" start="126.0"/><fov base="85.0" next="105.0"/><correct pan="0.0" tilt="0.0"/></chpano>
<chpano panoid="pano22"><range end="305.0" start="235.0"/><fov base="85.0" next="105.0"/><correct pan="0.0" tilt="0.0"/></chpano>
</chpanos>
</Panorama>
<Panorama panoid="pano15">
<img height="0" src="pano558.jpg" width="0"/>
<coords lat="34.66833055291665" lng="133.9162601530552"/>
<direction north="1180"/>
<chpanos>
<chpano panoid="pano7"><range end="125.0" start="44.0"/><fov base="85.0" next="105.0"/><correct pan="0.0" tilt="0.0"/></chpano>
<chpano panoid="pano14"><range end="234.0" start="126.0"/><fov base="85.0" next="105.0"/><correct pan="0.0" tilt="0.0"/></chpano>
<chpano panoid="pano32"><range end="309.0" start="235.0"/><fov base="85.0" next="105.0"/><correct pan="0.0" tilt="0.0"/></chpano>
</chpanos>
</Panorama>
<Panorama panoid="pano16">
<img height="0" src="pano559.jpg" width="0"/>
<coords lat="34.66819378044358" lng="133.916225284338"/>
<direction north="1180"/>
<chpanos>
<chpano panoid="pano17"><range end="34.0" start="305.0"/><fov base="85.0" next="105.0"/><correct pan="0.0" tilt="0.0"/></chpano>
<chpano panoid="pano8"><range end="139.0" start="35.0"/><fov base="85.0" next="105.0"/><correct pan="0.0" tilt="0.0"/></chpano>
<chpano panoid="pano24"><range end="304.0" start="213.0"/><fov base="85.0" next="105.0"/><correct pan="0.0" tilt="0.0"/></chpano>
</chpanos>
</Panorama>
<Panorama panoid="pano17">
<img height="0" src="pano560.jpg" width="0"/>
<coords lat="34.668213792083826" lng="133.91622509275163"/>
<direction north="1180"/>
<chpanos>
<chpano panoid="pano18"><range end="53.0" start="305.0"/><fov base="85.0" next="105.0"/><correct pan="0.0" tilt="0.0"/></chpano>
<chpano panoid="pano9"><range end="124.0" start="54.0"/><fov base="85.0" next="105.0"/><correct pan="0.0" tilt="0.0"/></chpano>
<chpano panoid="pano16"><range end="233.0" start="125.0"/><fov base="85.0" next="105.0"/><correct pan="0.0" tilt="0.0"/></chpano>
<chpano panoid="pano25"><range end="304.0" start="234.0"/><fov base="85.0" next="105.0"/><correct pan="0.0" tilt="0.0"/></chpano>
</chpanos>
</Panorama>
<Panorama panoid="pano18">
<img height="0" src="pano561.jpg" width="0"/>
<coords lat="34.668233803724064" lng="133.9162249011653"/>
<direction north="1180"/>
<chpanos>
<chpano panoid="pano19"><range end="53.0" start="305.0"/><fov base="85.0" next="105.0"/><correct pan="0.0" tilt="0.0"/></chpano>
<chpano panoid="pano10"><range end="124.0" start="54.0"/><fov base="85.0" next="105.0"/><correct pan="0.0" tilt="0.0"/></chpano>
<chpano panoid="pano17"><range end="233.0" start="125.0"/><fov base="85.0" next="105.0"/><correct pan="0.0" tilt="0.0"/></chpano>
<chpano panoid="pano26"><range end="304.0" start="234.0"/><fov base="85.0" next="105.0"/><correct pan="0.0" tilt="0.0"/></chpano>
</chpanos>
</Panorama>
<Panorama panoid="pano19">
<img height="0" src="pano562.jpg" width="0"/>
<coords lat="34.66825381536431" lng="133.91622470957893"/>
<direction north="1180"/>
<chpanos>
<chpano panoid="pano20"><range end="53.0" start="305.0"/><fov base="85.0" next="105.0"/><correct pan="0.0" tilt="0.0"/></chpano>
<chpano panoid="pano11"><range end="124.0" start="54.0"/><fov base="85.0" next="105.0"/><correct pan="0.0" tilt="0.0"/></chpano>
<chpano panoid="pano18"><range end="233.0" start="125.0"/><fov base="85.0" next="105.0"/><correct pan="0.0" tilt="0.0"/></chpano>
<chpano panoid="pano27"><range end="304.0" start="234.0"/><fov base="85.0" next="105.0"/><correct pan="0.0" tilt="0.0"/></chpano>
</chpanos>
</Panorama>
<Panorama panoid="pano20">
<img height="0" src="pano563.jpg" width="0"/>
<coords lat="34.668273827004555" lng="133.91622451799256"/>
<direction north="1180"/>
<chpanos>
<chpano panoid="pano21"><range end="53.0" start="305.0"/><fov base="85.0" next="105.0"/><correct pan="0.0" tilt="0.0"/></chpano>
<chpano panoid="pano12"><range end="124.0" start="54.0"/><fov base="85.0" next="105.0"/><correct pan="0.0" tilt="0.0"/></chpano>
<chpano panoid="pano19"><range end="233.0" start="125.0"/><fov base="85.0" next="105.0"/><correct pan="0.0" tilt="0.0"/></chpano>
<chpano panoid="pano28"><range end="304.0" start="234.0"/><fov base="85.0" next="105.0"/><correct pan="0.0" tilt="0.0"/></chpano>
</chpanos>
</Panorama>
<Panorama panoid="pano21">
<img height="0" src="pano564.jpg" width="0"/>
<coords lat="34.6682938386448" lng="133.9162243264062"/>
<direction north="1180"/>
<chpanos>
<chpano panoid="pano22"><range end="53.0" start="305.0"/><fov base="85.0" next="105.0"/><correct pan="0.0" tilt="0.0"/></chpano>
<chpano panoid="pano13"><range end="124.0" start="54.0"/><fov base="85.0" next="105.0"/><correct pan="0.0" tilt="0.0"/></chpano>
<chpano panoid="pano20"><range end="233.0" start="125.0"/><fov base="85.0" next="105.0"/><correct pan="0.0" tilt="0.0"/></chpano>
<chpano panoid="pano29"><range end="304.0" start="234.0"/><fov base="85.0" next="105.0"/><correct pan="0.0" tilt="0.0"/></chpano>
</chpanos>
</Panorama>
<Panorama panoid="pano22">
<img height="0" src="pano565.jpg" width="0"/>
<coords lat="34.66831385028504" lng="133.91622413481986"/>
<direction north="1180"/>
<chpanos>
<chpano panoid="pano23"><range end="53.0" start="305.0"/><fov base="85.0" next="105.0"/><correct pan="0.0" tilt="0.0"/></chpano>
<chpano panoid="pano14"><range end="124.0" start="54.0"/><fov base="85.0" next="105.0"/><correct pan="0.0" tilt="0.0"/></chpano>
<chpano panoid="pano21"><range end="233.0" start="125.0"/><fov base="85.0" next="105.0"/><correct pan="0.0" tilt="0.0"/></chpano>
<chpano panoid="pano30"><range end="304.0" start="234.0"/><fov base="85.0" next="105.0"/><correct pan="0.0" tilt="0.0"/></chpano>
</chpanos>
</Panorama>
<Panorama panoid="pano23">
<img height="0" src="pano566.jpg" width="0"/>
<coords lat="34.668333861925284" lng="133.9162239432335"/>
<direction north="1180"/>
<chpanos>
<chpano panoid="pano32"><range end="124.0" start="63.0"/><fov base="85.0" next="105.0"/><correct pan="0.0" tilt="0.0"/></chpano>
<chpano panoid="pano22"><range end="233.0" start="125.0"/><fov base="85.0" next="105.0"/><correct pan="0.0" tilt="0.0"/></chpano>
<chpano panoid="pano31"><range end="312.0" start="234.0"/><fov base="85.0" next="105.0"/><correct pan="0.0" tilt="0.0"/></chpano>
</chpanos>
</Panorama>
<Panorama panoid="pano24">
<img height="0" src="pano567.jpg" width="0"/>
<coords lat="34.668191574434104" lng="133.9161917567253"/>
<direction north="1180"/>
<chpanos>
<chpano panoid="pano25"><range end="32.0" start="306.0"/><fov base="85.0" next="105.0"/><correct pan="0.0" tilt="0.0"/></chpano>
<chpano panoid="pano16"><range end="137.0" start="33.0"/><fov base="85.0" next="105.0"/><correct pan="0.0" tilt="0.0"/></chpano>
</chpanos>
</Panorama>
<Panorama panoid="pano25">
<img height="0" src="pano568.jpg" width="0"/>
<coords lat="34.668211270931195" lng="133.9161917567253"/>
<direction north="1180"/>
<chpanos>
<chpano panoid="pano26"><range end="54.0" start="306.0"/><fov base="85.0" next="105.0"/><correct pan="0.0" tilt="0.0"/></chpano>
<chpano panoid="pano17"><range end="125.0" start="55.0"/><fov base="85.0" next="105.0"/><correct pan="0.0" tilt="0.0"/></chpano>
<chpano panoid="pano24"><range end="234.0" start="126.0"/><fov base="85.0" next="105.0"/><correct pan="0.0" tilt="0.0"/></chpano>
</chpanos>
</Panorama>
<Panorama panoid="pano26">
<img height="0" src="pano569.jpg" width="0"/>
<coords lat="34.668230967428286" lng="133.9161917567253"/>
<direction north="1180"/>
<chpanos>
<chpano panoid="pano27"><range end="54.0" start="306.0"/><fov base="85.0" next="105.0"/><correct pan="0.0" tilt="0.0"/></chpano>
<chpano panoid="pano18"><range end="125.0" start="55.0"/><fov base="85.0" next="105.0"/><correct pan="0.0" tilt="0.0"/></chpano>
<chpano panoid="pano25"><range end="234.0" start="126.0"/><fov base="85.0" next="105.0"/><correct pan="0.0" tilt="0.0"/></chpano>
</chpanos>
</Panorama>
<Panorama panoid="pano27">
<img height="0" src="pano570.jpg" width="0"/>
<coords lat="34.66825066392538" lng="133.9161917567253"/>
<direction north="1180"/>
<chpanos>
<chpano panoid="pano28"><range end="54.0" start="306.0"/><fov base="85.0" next="105.0"/><correct pan="0.0" tilt="0.0"/></chpano>
<chpano panoid="pano19"><range end="125.0" start="55.0"/><fov base="85.0" next="105.0"/><correct pan="0.0" tilt="0.0"/></chpano>
<chpano panoid="pano26"><range end="234.0" start="126.0"/><fov base="85.0" next="105.0"/><correct pan="0.0" tilt="0.0"/></chpano>
</chpanos>
</Panorama>
<Panorama panoid="pano28">
<img height="0" src="pano571.jpg" width="0"/>
<coords lat="34.668270360422476" lng="133.9161917567253"/>
<direction north="1180"/>
<chpanos>
<chpano panoid="pano29"><range end="54.0" start="306.0"/><fov base="85.0" next="105.0"/><correct pan="0.0" tilt="0.0"/></chpano>
<chpano panoid="pano20"><range end="125.0" start="55.0"/><fov base="85.0" next="105.0"/><correct pan="0.0" tilt="0.0"/></chpano>
<chpano panoid="pano27"><range end="234.0" start="126.0"/><fov base="85.0" next="105.0"/><correct pan="0.0" tilt="0.0"/></chpano>
</chpanos>
</Panorama>
<Panorama panoid="pano29">
<img height="0" src="pano572.jpg" width="0"/>
<coords lat="34.66829005691957" lng="133.9161917567253"/>
<direction north="1180"/>
<chpanos>
<chpano panoid="pano30"><range end="54.0" start="306.0"/><fov base="85.0" next="105.0"/><correct pan="0.0" tilt="0.0"/></chpano>
<chpano panoid="pano21"><range end="125.0" start="55.0"/><fov base="85.0" next="105.0"/><correct pan="0.0" tilt="0.0"/></chpano>
<chpano panoid="pano28"><range end="234.0" start="126.0"/><fov base="85.0" next="105.0"/><correct pan="0.0" tilt="0.0"/></chpano>
</chpanos>
</Panorama>
<Panorama panoid="pano30">
<img height="0" src="pano573.jpg" width="0"/>
<coords lat="34.66830975341666" lng="133.9161917567253"/>
<direction north="1180"/>
<chpanos>
<chpano panoid="pano31"><range end="54.0" start="306.0"/><fov base="85.0" next="105.0"/><correct pan="0.0" tilt="0.0"/></chpano>
<chpano panoid="pano22"><range end="125.0" start="55.0"/><fov base="85.0" next="105.0"/><correct pan="0.0" tilt="0.0"/></chpano>
<chpano panoid="pano29"><range end="234.0" start="126.0"/><fov base="85.0" next="105.0"/><correct pan="0.0" tilt="0.0"/></chpano>
</chpanos>
</Panorama>
<Panorama panoid="pano31">
<img height="0" src="pano574.jpg" width="0"/>
<coords lat="34.66832944991375" lng="133.9161917567253"/>
<direction north="1180"/>
<chpanos>
<chpano panoid="pano23"><range end="125.0" start="30.0"/><fov base="85.0" next="105.0"/><correct pan="0.0" tilt="0.0"/></chpano>
<chpano panoid="pano30"><range end="234.0" start="126.0"/><fov base="85.0" next="105.0"/><correct pan="0.0" tilt="0.0"/></chpano>
</chpanos>
</Panorama>
<Panorama panoid="pano32">
<img height="0" src="pano575.jpg" width="0"/>
<coords lat="34.66832614090491" lng="133.9162413775921"/>
<direction north="1180"/>
<chpanos>
<chpano panoid="pano15"><range end="77.0" start="19.0"/><fov base="85.0" next="105.0"/><correct pan="0.0" tilt="0.0"/></chpano>
<chpano panoid="pano14"><range end="186.0" start="78.0"/><fov base="85.0" next="105.0"/><correct pan="0.0" tilt="0.0"/></chpano>
<chpano panoid="pano22"><range end="283.0" start="187.0"/><fov base="85.0" next="105.0"/><correct pan="0.0" tilt="0.0"/></chpano>
<chpano panoid="pano23"><range end="353.0" start="284.0"/><fov base="85.0" next="105.0"/><correct pan="0.0" tilt="0.0"/></chpano>
</chpanos>
</Panorama>
</Panoramas>
</PCD>