<?xml version="1.0" encoding="UTF-8"?><PCD>
<Panoramas startdir="260" startpano="pano8" startfloor="8F"startcont="01" startname="シアター">
<Panorama panoid="pano0">
<img height="0" src="pano364.jpg" width="0"/>
<coords lat="34.66831080916903" lng="133.91649551689625"/>
<direction north="1180"/>
<chpanos>
<chpano panoid="pano8"><range end="217.0" start="131.0"/><fov base="85.0" next="105.0"/><correct pan="0.0" tilt="0.0"/></chpano>
<chpano panoid="pano1"><range end="320.0" start="218.0"/><fov base="85.0" next="105.0"/><correct pan="0.0" tilt="0.0"/></chpano>
</chpanos>
</Panorama>
<Panorama panoid="pano1">
<img height="0" src="pano365.jpg" width="0"/>
<coords lat="34.66831079341088" lng="133.9164544216224"/>
<direction north="1180"/>
<chpanos>
<chpano panoid="pano0"><range end="140.0" start="38.0"/><fov base="85.0" next="105.0"/><correct pan="0.0" tilt="0.0"/></chpano>
<chpano panoid="pano9"><range end="217.0" start="141.0"/><fov base="85.0" next="105.0"/><correct pan="0.0" tilt="0.0"/></chpano>
<chpano panoid="pano2"><range end="320.0" start="218.0"/><fov base="85.0" next="105.0"/><correct pan="0.0" tilt="0.0"/></chpano>
</chpanos>
</Panorama>
<Panorama panoid="pano2">
<img height="0" src="pano366.jpg" width="0"/>
<coords lat="34.668310777652735" lng="133.9164133263486"/>
<direction north="1180"/>
<chpanos>
<chpano panoid="pano1"><range end="140.0" start="38.0"/><fov base="85.0" next="105.0"/><correct pan="0.0" tilt="0.0"/></chpano>
<chpano panoid="pano10"><range end="217.0" start="141.0"/><fov base="85.0" next="105.0"/><correct pan="0.0" tilt="0.0"/></chpano>
<chpano panoid="pano3"><range end="320.0" start="218.0"/><fov base="85.0" next="105.0"/><correct pan="0.0" tilt="0.0"/></chpano>
</chpanos>
</Panorama>
<Panorama panoid="pano3">
<img height="0" src="pano367.jpg" width="0"/>
<coords lat="34.66831076189459" lng="133.91637223107475"/>
<direction north="1180"/>
<chpanos>
<chpano panoid="pano2"><range end="140.0" start="38.0"/><fov base="85.0" next="105.0"/><correct pan="0.0" tilt="0.0"/></chpano>
<chpano panoid="pano11"><range end="217.0" start="141.0"/><fov base="85.0" next="105.0"/><correct pan="0.0" tilt="0.0"/></chpano>
<chpano panoid="pano4"><range end="320.0" start="218.0"/><fov base="85.0" next="105.0"/><correct pan="0.0" tilt="0.0"/></chpano>
</chpanos>
</Panorama>
<Panorama panoid="pano4">
<img height="0" src="pano368.jpg" width="0"/>
<coords lat="34.66831074613644" lng="133.9163311358009"/>
<direction north="1180"/>
<chpanos>
<chpano panoid="pano3"><range end="140.0" start="38.0"/><fov base="85.0" next="105.0"/><correct pan="0.0" tilt="0.0"/></chpano>
<chpano panoid="pano12"><range end="217.0" start="141.0"/><fov base="85.0" next="105.0"/><correct pan="0.0" tilt="0.0"/></chpano>
<chpano panoid="pano5"><range end="320.0" start="218.0"/><fov base="85.0" next="105.0"/><correct pan="0.0" tilt="0.0"/></chpano>
</chpanos>
</Panorama>
<Panorama panoid="pano5">
<img height="0" src="pano369.jpg" width="0"/>
<coords lat="34.668310730378295" lng="133.91629004052706"/>
<direction north="1180"/>
<chpanos>
<chpano panoid="pano4"><range end="140.0" start="38.0"/><fov base="85.0" next="105.0"/><correct pan="0.0" tilt="0.0"/></chpano>
<chpano panoid="pano13"><range end="217.0" start="141.0"/><fov base="85.0" next="105.0"/><correct pan="0.0" tilt="0.0"/></chpano>
<chpano panoid="pano6"><range end="320.0" start="218.0"/><fov base="85.0" next="105.0"/><correct pan="0.0" tilt="0.0"/></chpano>
</chpanos>
</Panorama>
<Panorama panoid="pano6">
<img height="0" src="pano370.jpg" width="0"/>
<coords lat="34.66831071462015" lng="133.91624894525324"/>
<direction north="1180"/>
<chpanos>
<chpano panoid="pano5"><range end="140.0" start="38.0"/><fov base="85.0" next="105.0"/><correct pan="0.0" tilt="0.0"/></chpano>
<chpano panoid="pano14"><range end="217.0" start="141.0"/><fov base="85.0" next="105.0"/><correct pan="0.0" tilt="0.0"/></chpano>
<chpano panoid="pano7"><range end="320.0" start="218.0"/><fov base="85.0" next="105.0"/><correct pan="0.0" tilt="0.0"/></chpano>
</chpanos>
</Panorama>
<Panorama panoid="pano7">
<img height="0" src="pano371.jpg" width="0"/>
<coords lat="34.668310698862" lng="133.91619846224785"/>
<direction north="1180"/>
<chpanos>
<chpano panoid="pano6"><range end="140.0" start="38.0"/><fov base="85.0" next="105.0"/><correct pan="0.0" tilt="0.0"/></chpano>
<chpano panoid="pano15"><range end="235.0" start="141.0"/><fov base="85.0" next="105.0"/><correct pan="0.0" tilt="0.0"/></chpano>
</chpanos>
</Panorama>
<Panorama panoid="pano8">
<img height="0" src="pano372.jpg" width="0"/>
<coords lat="34.66826889503806" lng="133.91649551689625"/>
<direction north="1180"/>
<chpanos>
<chpano panoid="pano0"><range end="49.0" start="311.0"/><fov base="85.0" next="105.0"/><correct pan="0.0" tilt="0.0"/></chpano>
<chpano panoid="pano16"><range end="218.0" start="127.0"/><fov base="85.0" next="105.0"/><correct pan="0.0" tilt="0.0"/></chpano>
<chpano panoid="pano32"><range end="218.0" start="128.0"/><fov base="85.0" next="105.0"/><correct pan="0.0" tilt="0.0"/></chpano>
<chpano panoid="pano9"><range end="310.0" start="219.0"/><fov base="85.0" next="105.0"/><correct pan="0.0" tilt="0.0"/></chpano>
</chpanos>
</Panorama>
<Panorama panoid="pano9">
<img height="0" src="pano373.jpg" width="0"/>
<coords lat="34.66826903685187" lng="133.91645365527697"/>
<direction north="1180"/>
<chpanos>
<chpano panoid="pano1"><range end="49.0" start="311.0"/><fov base="85.0" next="105.0"/><correct pan="0.0" tilt="0.0"/></chpano>
<chpano panoid="pano8"><range end="141.0" start="50.0"/><fov base="85.0" next="105.0"/><correct pan="0.0" tilt="0.0"/></chpano>
<chpano panoid="pano17"><range end="218.0" start="142.0"/><fov base="85.0" next="105.0"/><correct pan="0.0" tilt="0.0"/></chpano>
<chpano panoid="pano10"><range end="310.0" start="219.0"/><fov base="85.0" next="105.0"/><correct pan="0.0" tilt="0.0"/></chpano>
</chpanos>
</Panorama>
<Panorama panoid="pano10">
<img height="0" src="pano374.jpg" width="0"/>
<coords lat="34.668269178665675" lng="133.91641179365772"/>
<direction north="1180"/>
<chpanos>
<chpano panoid="pano2"><range end="50.0" start="312.0"/><fov base="85.0" next="105.0"/><correct pan="0.0" tilt="0.0"/></chpano>
<chpano panoid="pano9"><range end="141.0" start="51.0"/><fov base="85.0" next="105.0"/><correct pan="0.0" tilt="0.0"/></chpano>
<chpano panoid="pano18"><range end="218.0" start="142.0"/><fov base="85.0" next="105.0"/><correct pan="0.0" tilt="0.0"/></chpano>
<chpano panoid="pano11"><range end="311.0" start="219.0"/><fov base="85.0" next="105.0"/><correct pan="0.0" tilt="0.0"/></chpano>
</chpanos>
</Panorama>
<Panorama panoid="pano11">
<img height="0" src="pano375.jpg" width="0"/>
<coords lat="34.66826932047948" lng="133.91636993203844"/>
<direction north="1180"/>
<chpanos>
<chpano panoid="pano3"><range end="51.0" start="313.0"/><fov base="85.0" next="105.0"/><correct pan="0.0" tilt="0.0"/></chpano>
<chpano panoid="pano10"><range end="141.0" start="52.0"/><fov base="85.0" next="105.0"/><correct pan="0.0" tilt="0.0"/></chpano>
<chpano panoid="pano19"><range end="218.0" start="142.0"/><fov base="85.0" next="105.0"/><correct pan="0.0" tilt="0.0"/></chpano>
<chpano panoid="pano12"><range end="312.0" start="219.0"/><fov base="85.0" next="105.0"/><correct pan="0.0" tilt="0.0"/></chpano>
</chpanos>
</Panorama>
<Panorama panoid="pano12">
<img height="0" src="pano376.jpg" width="0"/>
<coords lat="34.66826946229328" lng="133.91632807041918"/>
<direction north="1180"/>
<chpanos>
<chpano panoid="pano4"><range end="52.0" start="314.0"/><fov base="85.0" next="105.0"/><correct pan="0.0" tilt="0.0"/></chpano>
<chpano panoid="pano11"><range end="141.0" start="53.0"/><fov base="85.0" next="105.0"/><correct pan="0.0" tilt="0.0"/></chpano>
<chpano panoid="pano20"><range end="218.0" start="142.0"/><fov base="85.0" next="105.0"/><correct pan="0.0" tilt="0.0"/></chpano>
<chpano panoid="pano13"><range end="313.0" start="219.0"/><fov base="85.0" next="105.0"/><correct pan="0.0" tilt="0.0"/></chpano>
</chpanos>
</Panorama>
<Panorama panoid="pano13">
<img height="0" src="pano377.jpg" width="0"/>
<coords lat="34.66826960410709" lng="133.9162862087999"/>
<direction north="1180"/>
<chpanos>
<chpano panoid="pano5"><range end="53.0" start="315.0"/><fov base="85.0" next="105.0"/><correct pan="0.0" tilt="0.0"/></chpano>
<chpano panoid="pano12"><range end="141.0" start="54.0"/><fov base="85.0" next="105.0"/><correct pan="0.0" tilt="0.0"/></chpano>
<chpano panoid="pano21"><range end="218.0" start="142.0"/><fov base="85.0" next="105.0"/><correct pan="0.0" tilt="0.0"/></chpano>
<chpano panoid="pano14"><range end="314.0" start="219.0"/><fov base="85.0" next="105.0"/><correct pan="0.0" tilt="0.0"/></chpano>
</chpanos>
</Panorama>
<Panorama panoid="pano14">
<img height="0" src="pano378.jpg" width="0"/>
<coords lat="34.668269745920895" lng="133.91624434718065"/>
<direction north="1180"/>
<chpanos>
<chpano panoid="pano6"><range end="54.0" start="316.0"/><fov base="85.0" next="105.0"/><correct pan="0.0" tilt="0.0"/></chpano>
<chpano panoid="pano13"><range end="141.0" start="55.0"/><fov base="85.0" next="105.0"/><correct pan="0.0" tilt="0.0"/></chpano>
<chpano panoid="pano22"><range end="218.0" start="142.0"/><fov base="85.0" next="105.0"/><correct pan="0.0" tilt="0.0"/></chpano>
<chpano panoid="pano15"><range end="315.0" start="219.0"/><fov base="85.0" next="105.0"/><correct pan="0.0" tilt="0.0"/></chpano>
</chpanos>
</Panorama>
<Panorama panoid="pano15">
<img height="0" src="pano379.jpg" width="0"/>
<coords lat="34.6682698877347" lng="133.91620248556137"/>
<direction north="1180"/>
<chpanos>
<chpano panoid="pano7"><range end="55.0" start="317.0"/><fov base="85.0" next="105.0"/><correct pan="0.0" tilt="0.0"/></chpano>
<chpano panoid="pano14"><range end="141.0" start="56.0"/><fov base="85.0" next="105.0"/><correct pan="0.0" tilt="0.0"/></chpano>
<chpano panoid="pano23"><range end="235.0" start="142.0"/><fov base="85.0" next="105.0"/><correct pan="0.0" tilt="0.0"/></chpano>
</chpanos>
</Panorama>
<Panorama panoid="pano16">
<img height="0" src="pano380.jpg" width="0"/>
<coords lat="34.668230179591525" lng="133.916497528553"/>
<direction north="1180"/>
<chpanos>
<chpano panoid="pano8"><range end="47.0" start="307.0"/><fov base="85.0" next="105.0"/><correct pan="0.0" tilt="0.0"/></chpano>
<chpano panoid="pano24"><range end="219.0" start="131.0"/><fov base="85.0" next="105.0"/><correct pan="0.0" tilt="0.0"/></chpano>
<chpano panoid="pano17"><range end="306.0" start="220.0"/><fov base="85.0" next="105.0"/><correct pan="0.0" tilt="0.0"/></chpano>
</chpanos>
</Panorama>
<Panorama panoid="pano17">
<img height="0" src="pano381.jpg" width="0"/>
<coords lat="34.668230179591525" lng="133.91645461320877"/>
<direction north="1180"/>
<chpanos>
<chpano panoid="pano9"><range end="48.0" start="308.0"/><fov base="85.0" next="105.0"/><correct pan="0.0" tilt="0.0"/></chpano>
<chpano panoid="pano16"><range end="140.0" start="49.0"/><fov base="85.0" next="105.0"/><correct pan="0.0" tilt="0.0"/></chpano>
<chpano panoid="pano25"><range end="219.0" start="141.0"/><fov base="85.0" next="105.0"/><correct pan="0.0" tilt="0.0"/></chpano>
<chpano panoid="pano18"><range end="307.0" start="220.0"/><fov base="85.0" next="105.0"/><correct pan="0.0" tilt="0.0"/></chpano>
</chpanos>
</Panorama>
<Panorama panoid="pano18">
<img height="0" src="pano382.jpg" width="0"/>
<coords lat="34.668230179591525" lng="133.91641169786453"/>
<direction north="1180"/>
<chpanos>
<chpano panoid="pano10"><range end="50.0" start="310.0"/><fov base="85.0" next="105.0"/><correct pan="0.0" tilt="0.0"/></chpano>
<chpano panoid="pano17"><range end="140.0" start="51.0"/><fov base="85.0" next="105.0"/><correct pan="0.0" tilt="0.0"/></chpano>
<chpano panoid="pano26"><range end="219.0" start="141.0"/><fov base="85.0" next="105.0"/><correct pan="0.0" tilt="0.0"/></chpano>
<chpano panoid="pano19"><range end="309.0" start="220.0"/><fov base="85.0" next="105.0"/><correct pan="0.0" tilt="0.0"/></chpano>
</chpanos>
</Panorama>
<Panorama panoid="pano19">
<img height="0" src="pano383.jpg" width="0"/>
<coords lat="34.668230179591525" lng="133.9163687825203"/>
<direction north="1180"/>
<chpanos>
<chpano panoid="pano11"><range end="50.0" start="312.0"/><fov base="85.0" next="105.0"/><correct pan="0.0" tilt="0.0"/></chpano>
<chpano panoid="pano18"><range end="140.0" start="51.0"/><fov base="85.0" next="105.0"/><correct pan="0.0" tilt="0.0"/></chpano>
<chpano panoid="pano27"><range end="219.0" start="141.0"/><fov base="85.0" next="105.0"/><correct pan="0.0" tilt="0.0"/></chpano>
<chpano panoid="pano20"><range end="311.0" start="220.0"/><fov base="85.0" next="105.0"/><correct pan="0.0" tilt="0.0"/></chpano>
</chpanos>
</Panorama>
<Panorama panoid="pano20">
<img height="0" src="pano384.jpg" width="0"/>
<coords lat="34.668230179591525" lng="133.91632586717606"/>
<direction north="1180"/>
<chpanos>
<chpano panoid="pano12"><range end="51.0" start="313.0"/><fov base="85.0" next="105.0"/><correct pan="0.0" tilt="0.0"/></chpano>
<chpano panoid="pano19"><range end="140.0" start="52.0"/><fov base="85.0" next="105.0"/><correct pan="0.0" tilt="0.0"/></chpano>
<chpano panoid="pano28"><range end="219.0" start="141.0"/><fov base="85.0" next="105.0"/><correct pan="0.0" tilt="0.0"/></chpano>
<chpano panoid="pano21"><range end="312.0" start="220.0"/><fov base="85.0" next="105.0"/><correct pan="0.0" tilt="0.0"/></chpano>
</chpanos>
</Panorama>
<Panorama panoid="pano21">
<img height="0" src="pano385.jpg" width="0"/>
<coords lat="34.668230179591525" lng="133.91628295183182"/>
<direction north="1180"/>
<chpanos>
<chpano panoid="pano13"><range end="52.0" start="314.0"/><fov base="85.0" next="105.0"/><correct pan="0.0" tilt="0.0"/></chpano>
<chpano panoid="pano20"><range end="140.0" start="53.0"/><fov base="85.0" next="105.0"/><correct pan="0.0" tilt="0.0"/></chpano>
<chpano panoid="pano29"><range end="219.0" start="141.0"/><fov base="85.0" next="105.0"/><correct pan="0.0" tilt="0.0"/></chpano>
<chpano panoid="pano22"><range end="313.0" start="220.0"/><fov base="85.0" next="105.0"/><correct pan="0.0" tilt="0.0"/></chpano>
</chpanos>
</Panorama>
<Panorama panoid="pano22">
<img height="0" src="pano386.jpg" width="0"/>
<coords lat="34.668230179591525" lng="133.91624003648758"/>
<direction north="1180"/>
<chpanos>
<chpano panoid="pano14"><range end="54.0" start="316.0"/><fov base="85.0" next="105.0"/><correct pan="0.0" tilt="0.0"/></chpano>
<chpano panoid="pano21"><range end="140.0" start="55.0"/><fov base="85.0" next="105.0"/><correct pan="0.0" tilt="0.0"/></chpano>
<chpano panoid="pano30"><range end="219.0" start="141.0"/><fov base="85.0" next="105.0"/><correct pan="0.0" tilt="0.0"/></chpano>
<chpano panoid="pano23"><range end="315.0" start="220.0"/><fov base="85.0" next="105.0"/><correct pan="0.0" tilt="0.0"/></chpano>
</chpanos>
</Panorama>
<Panorama panoid="pano23">
<img height="0" src="pano387.jpg" width="0"/>
<coords lat="34.668230179591525" lng="133.91619712114334"/>
<direction north="1180"/>
<chpanos>
<chpano panoid="pano15"><range end="55.0" start="317.0"/><fov base="85.0" next="105.0"/><correct pan="0.0" tilt="0.0"/></chpano>
<chpano panoid="pano22"><range end="140.0" start="56.0"/><fov base="85.0" next="105.0"/><correct pan="0.0" tilt="0.0"/></chpano>
<chpano panoid="pano31"><range end="233.0" start="141.0"/><fov base="85.0" next="105.0"/><correct pan="0.0" tilt="0.0"/></chpano>
</chpanos>
</Panorama>
<Panorama panoid="pano24">
<img height="0" src="pano388.jpg" width="0"/>
<coords lat="34.66818716241496" lng="133.916497528553"/>
<direction north="1180"/>
<chpanos>
<chpano panoid="pano16"><range end="49.0" start="311.0"/><fov base="85.0" next="105.0"/><correct pan="0.0" tilt="0.0"/></chpano>
<chpano panoid="pano25"><range end="310.0" start="220.0"/><fov base="85.0" next="105.0"/><correct pan="0.0" tilt="0.0"/></chpano>
</chpanos>
</Panorama>
<Panorama panoid="pano25">
<img height="0" src="pano389.jpg" width="0"/>
<coords lat="34.66818747755919" lng="133.9164540384497"/>
<direction north="1180"/>
<chpanos>
<chpano panoid="pano17"><range end="49.0" start="311.0"/><fov base="85.0" next="105.0"/><correct pan="0.0" tilt="0.0"/></chpano>
<chpano panoid="pano24"><range end="140.0" start="50.0"/><fov base="85.0" next="105.0"/><correct pan="0.0" tilt="0.0"/></chpano>
<chpano panoid="pano26"><range end="310.0" start="220.0"/><fov base="85.0" next="105.0"/><correct pan="0.0" tilt="0.0"/></chpano>
</chpanos>
</Panorama>
<Panorama panoid="pano26">
<img height="0" src="pano390.jpg" width="0"/>
<coords lat="34.668187792703414" lng="133.9164105483464"/>
<direction north="1180"/>
<chpanos>
<chpano panoid="pano18"><range end="50.0" start="312.0"/><fov base="85.0" next="105.0"/><correct pan="0.0" tilt="0.0"/></chpano>
<chpano panoid="pano25"><range end="140.0" start="51.0"/><fov base="85.0" next="105.0"/><correct pan="0.0" tilt="0.0"/></chpano>
<chpano panoid="pano27"><range end="311.0" start="220.0"/><fov base="85.0" next="105.0"/><correct pan="0.0" tilt="0.0"/></chpano>
</chpanos>
</Panorama>
<Panorama panoid="pano27">
<img height="0" src="pano391.jpg" width="0"/>
<coords lat="34.66818810784764" lng="133.91636705824308"/>
<direction north="1180"/>
<chpanos>
<chpano panoid="pano19"><range end="50.0" start="312.0"/><fov base="85.0" next="105.0"/><correct pan="0.0" tilt="0.0"/></chpano>
<chpano panoid="pano26"><range end="140.0" start="51.0"/><fov base="85.0" next="105.0"/><correct pan="0.0" tilt="0.0"/></chpano>
<chpano panoid="pano28"><range end="311.0" start="220.0"/><fov base="85.0" next="105.0"/><correct pan="0.0" tilt="0.0"/></chpano>
</chpanos>
</Panorama>
<Panorama panoid="pano28">
<img height="0" src="pano392.jpg" width="0"/>
<coords lat="34.668188422991875" lng="133.91632356813975"/>
<direction north="1180"/>
<chpanos>
<chpano panoid="pano20"><range end="51.0" start="313.0"/><fov base="85.0" next="105.0"/><correct pan="0.0" tilt="0.0"/></chpano>
<chpano panoid="pano27"><range end="140.0" start="52.0"/><fov base="85.0" next="105.0"/><correct pan="0.0" tilt="0.0"/></chpano>
<chpano panoid="pano29"><range end="312.0" start="220.0"/><fov base="85.0" next="105.0"/><correct pan="0.0" tilt="0.0"/></chpano>
</chpanos>
</Panorama>
<Panorama panoid="pano29">
<img height="0" src="pano393.jpg" width="0"/>
<coords lat="34.6681887381361" lng="133.91628007803644"/>
<direction north="1180"/>
<chpanos>
<chpano panoid="pano21"><range end="52.0" start="314.0"/><fov base="85.0" next="105.0"/><correct pan="0.0" tilt="0.0"/></chpano>
<chpano panoid="pano28"><range end="140.0" start="53.0"/><fov base="85.0" next="105.0"/><correct pan="0.0" tilt="0.0"/></chpano>
<chpano panoid="pano30"><range end="313.0" start="220.0"/><fov base="85.0" next="105.0"/><correct pan="0.0" tilt="0.0"/></chpano>
</chpanos>
</Panorama>
<Panorama panoid="pano30">
<img height="0" src="pano394.jpg" width="0"/>
<coords lat="34.66818905328033" lng="133.91623658793313"/>
<direction north="1180"/>
<chpanos>
<chpano panoid="pano22"><range end="52.0" start="314.0"/><fov base="85.0" next="105.0"/><correct pan="0.0" tilt="0.0"/></chpano>
<chpano panoid="pano29"><range end="140.0" start="53.0"/><fov base="85.0" next="105.0"/><correct pan="0.0" tilt="0.0"/></chpano>
<chpano panoid="pano31"><range end="313.0" start="220.0"/><fov base="85.0" next="105.0"/><correct pan="0.0" tilt="0.0"/></chpano>
</chpanos>
</Panorama>
<Panorama panoid="pano31">
<img height="0" src="pano395.jpg" width="0"/>
<coords lat="34.66818936842456" lng="133.91619309782982"/>
<direction north="1180"/>
<chpanos>
<chpano panoid="pano23"><range end="53.0" start="315.0"/><fov base="85.0" next="105.0"/><correct pan="0.0" tilt="0.0"/></chpano>
<chpano panoid="pano30"><range end="140.0" start="54.0"/><fov base="85.0" next="105.0"/><correct pan="0.0" tilt="0.0"/></chpano>
</chpanos>
</Panorama>
<Panorama panoid="pano32">
<img height="0" src="pano542.jpg" width="0"/>
<coords lat="34.668262166708345" lng="133.91654178500175"/>
<direction north="1180"/>
<chpanos>
<chpano panoid="pano33"><range end="139.0" start="41.0"/><fov base="85.0" next="105.0"/><correct pan="0.0" tilt="0.0"/></chpano>
<chpano panoid="pano8"><range end="319.0" start="221.0"/><fov base="85.0" next="105.0"/><correct pan="0.0" tilt="0.0"/></chpano>
</chpanos>
</Panorama>
<Panorama panoid="pano33">
<img height="0" src="pano541.jpg" width="0"/>
<coords lat="34.668262166708345" lng="133.91659006476402"/>
<direction north="1180"/>
<chpanos>
<chpano panoid="pano32"><range end="319.0" start="221.0"/><fov base="85.0" next="105.0"/><correct pan="0.0" tilt="0.0"/></chpano>
<chpano panoid=""></chpano>
</chpanos>
</Panorama>
</Panoramas>
</PCD>